domplus/__init__.py
domplus/finance.py
domplus/gov/__init__.py
domplus/gov/br/__init__.py
domplus/gov/br/br.py
domplus-1.0.3.dist-info/LICENSE
domplus-1.0.3.dist-info/METADATA
domplus-1.0.3.dist-info/WHEEL
domplus-1.0.3.dist-info/RECORD
