Metadata-Version: 2.1
Name: domplus
Version: 1.0.3
Summary: domplus is a python package with common functions for commercial applications.
License: MIT
Keywords: validation,cpf,cnpj,creditcard,uhn-algorithm
Author: Eduardo Basílio
Author-email: eduardoafonsobasilio@gmail.com
Requires-Python: >=3.8,<4.0
Classifier: License :: OSI Approved :: MIT License
Classifier: Programming Language :: Python :: 3
Classifier: Programming Language :: Python :: 3.8
Classifier: Programming Language :: Python :: 3.9
Classifier: Programming Language :: Python :: 3.10
Classifier: Programming Language :: Python :: 3.11
